agentChef/__init__.py
agentChef/main.py
agentChef/api/agent_chef_api.py
agentChef/cli/__init__.py
agentChef/cli/help_texts.py
agentChef/cli/main.py
agentChef/config/__init__.py
agentChef/config/config.py
agentChef/config/config_editor.py
agentChef/config/config_manager.py
agentChef/config/config_validators.py
agentChef/core/__init__.py
agentChef/core/augmentation/__init__.py
agentChef/core/augmentation/dataset_expander.py
agentChef/core/chefs/__init__.py
agentChef/core/chefs/base_chef.py
agentChef/core/chefs/pandas_rag.py
agentChef/core/chefs/personal_research_assistant.py
agentChef/core/chefs/ragchef.py
agentChef/core/classification/__init__.py
agentChef/core/classification/classification.py
agentChef/core/classification/dataset_cleaner.py
agentChef/core/crawlers/__init__.py
agentChef/core/crawlers/crawlers_module.py
agentChef/core/generation/__init__.py
agentChef/core/generation/conversation_generator.py
agentChef/core/img_annotation/__init__.py
agentChef/core/img_annotation/img_text_annotation_csv.py
agentChef/core/llamaindex/__init__.py
agentChef/core/llamaindex/pandas_query.py
agentChef/core/ollama/__init__.py
agentChef/core/ollama/ollama_interface.py
agentChef/core/ui_components/__init__.py
agentChef/core/ui_components/menu_module.py
agentChef/logs/__init__.py
agentChef/logs/agentchef_logging.py
agentChef/logs/setup.py
agentChef/mcp/__init__.py
agentChef/mcp/mcp_manager.py
agentChef/mcp/mcp_server.py
agentChef/utils/__init__.py
agentChef/utils/build_utils.py
agentChef/utils/const.py
agentChef/utils/decorators.py
agentChef/utils/mcp_utils.py
agentChef/utils/paths.py
agentChef/utils/storage_utils.py
agentchef-0.2.12.dist-info/licenses/LICENSE
agentchef-0.2.12.dist-info/METADATA
agentchef-0.2.12.dist-info/WHEEL
agentchef-0.2.12.dist-info/entry_points.txt
agentchef-0.2.12.dist-info/top_level.txt
agentchef-0.2.12.dist-info/RECORD
