Metadata-Version: 2.4
Name: agentChef
Version: 0.2.12
Summary: Comprehensive toolkit for conversation dataset creation, augmentation, and analysis
Author-email: oll4m404rc <notsetup@gmail.com>
License-Expression: Apache-2.0
Project-URL: Homepage, https://github.com/Leoleojames1/agentChef
Project-URL: Bug Tracker, https://github.com/Leoleojames1/agentChef/issues
Project-URL: Documentation, https://github.com/Leoleojames1/agentChef/blob/main/README.md
Keywords: conversation,dataset,augmentation,generation,ollama,ai
Classifier: Programming Language :: Python :: 3.11
Classifier: Programming Language :: Python :: 3.12
Classifier: Programming Language :: Python :: 3.13
Classifier: Operating System :: OS Independent
Classifier: Development Status :: 4 - Beta
Classifier: Intended Audience :: Developers
Classifier: Intended Audience :: Science/Research
Classifier: Topic :: Scientific/Engineering :: Artificial Intelligence
Requires-Python: >=3.11
License-File: LICENSE
Requires-Dist: aiohttp>=3.11.16
Requires-Dist: beautifulsoup4>=3.2.2
Requires-Dist: duckduckgo-search>=8.0.2
Requires-Dist: gitpython>=3.1.44
Requires-Dist: llama-index>=0.12.26
Requires-Dist: llama-index-experimental>=0.5.6
Requires-Dist: matplotlib>=3.10.1
Requires-Dist: numpy>=2.3.0
Requires-Dist: ollama>=0.5.1
Requires-Dist: pandas>=2.2.3
Requires-Dist: pyyaml>=6.0.2
Requires-Dist: PyQt6>=6.8.1
Requires-Dist: requests>=2.32.3
Requires-Dist: seaborn>=0.13.2
Requires-Dist: tqdm>=4.67.1
Requires-Dist: oarc-crawlers>=0.1.14
Requires-Dist: PyQt6-WebEngine>=6.4.0
Requires-Dist: pyvis>=0.3.2
Requires-Dist: PySDL3>=0.9.8b5
Provides-Extra: dev
Requires-Dist: black>=25.1.0; extra == "dev"
Requires-Dist: isort>=6.0.1; extra == "dev"
Requires-Dist: flake8>=7.2.0; extra == "dev"
Requires-Dist: pytest>=8.3.5; extra == "dev"
Requires-Dist: twine>=6.1.0; extra == "dev"
Requires-Dist: build>=1.2.2.post1; extra == "dev"
Dynamic: license-file
